terminal_style/__init__.py
terminal_style/config_styles.yml
terminal_style/spinner.py
terminal_style/terminal_style.py
terminal_style/terminal_style_config.py
terminal_style-0.0.4.dist-info/METADATA
terminal_style-0.0.4.dist-info/WHEEL
terminal_style-0.0.4.dist-info/licenses/LICENSE
terminal_style-0.0.4.dist-info/RECORD
