Metadata-Version: 2.4
Name: terminal-style
Version: 0.0.4
Summary: Style your terminal-printed text
Project-URL: homepage, https://github.com/colinfrisch/terminal-style
Project-URL: repository, https://github.com/colinfrisch/terminal-style
License: MIT
License-File: LICENSE
Keywords: backgrounds,colors,effects,formatting,style,styling,terminal,text
Classifier: Intended Audience :: Developers
Classifier: Intended Audience :: End Users/Desktop
Classifier: Intended Audience :: Science/Research
Classifier: Intended Audience :: System Administrators
Classifier: License :: OSI Approved :: MIT License
Classifier: Natural Language :: English
Classifier: Operating System :: OS Independent
Classifier: Programming Language :: Python :: 3 :: Only
Classifier: Programming Language :: Python :: 3.11
Classifier: Programming Language :: Python :: 3.12
Classifier: Programming Language :: Python :: 3.13
Requires-Python: >=3.7
Requires-Dist: pyyaml
Provides-Extra: all
Requires-Dist: black[jupyter]; extra == 'all'
Requires-Dist: build; extra == 'all'
Requires-Dist: coverage; extra == 'all'
Requires-Dist: ipython; extra == 'all'
Requires-Dist: mypy; extra == 'all'
Requires-Dist: pre-commit; extra == 'all'
Requires-Dist: pytest-cov; extra == 'all'
Requires-Dist: pytest-mock; extra == 'all'
Requires-Dist: pytest>=4.6; extra == 'all'
Requires-Dist: ruff; extra == 'all'
Requires-Dist: sphinx; extra == 'all'
Requires-Dist: twine; extra == 'all'
Provides-Extra: dev
Requires-Dist: black[jupyter]; extra == 'dev'
Requires-Dist: build; extra == 'dev'
Requires-Dist: coverage; extra == 'dev'
Requires-Dist: mypy; extra == 'dev'
Requires-Dist: pre-commit; extra == 'dev'
Requires-Dist: pytest-cov; extra == 'dev'
Requires-Dist: pytest-mock; extra == 'dev'
Requires-Dist: pytest>=4.6; extra == 'dev'
Requires-Dist: ruff; extra == 'dev'
Requires-Dist: sphinx; extra == 'dev'
Requires-Dist: twine; extra == 'dev'
Provides-Extra: docs
Requires-Dist: ipython; extra == 'docs'
Requires-Dist: sphinx; extra == 'docs'
